hierarchical_state_machine/__init__.py
hierarchical_state_machine/state_machine_state.py
hierarchical_state_machine/example/pedestrian_crosswalk/ascii_crosswalk.py
hierarchical_state_machine/example/pedestrian_crosswalk/crosswalk_light_simulator.py
hierarchical_state_machine/example/pedestrian_crosswalk/hierarchical_example_pedestrian_crosswalk_signaler.pdf
hierarchical_state_machine/tests/__init__.py
hierarchical_state_machine-1.0.16.dist-info/LICENSE.txt
hierarchical_state_machine-1.0.16.dist-info/METADATA
hierarchical_state_machine-1.0.16.dist-info/WHEEL
hierarchical_state_machine-1.0.16.dist-info/top_level.txt
hierarchical_state_machine-1.0.16.dist-info/RECORD
