Metadata-Version: 2.1
Name: hierarchical_state_machine
Version: 1.0.16
Summary: This python library provides an easy-to-learn and easy-to-use API for using Hierarchical State Machines in your project. The state machine is defined using a basic JSON string, and includes convenience timers.
Author-email: Dan Tebbs <dantebbs@gmail.com>
License: MIT License
Project-URL: Repository, https://github.com/dantebbs/hierarchical_state_machine
Keywords: hierarchical,state,machine,hsm,State Machine,State-Machine,statemachine,sm
Classifier: Programming Language :: Python :: 3
Classifier: Programming Language :: Python :: 3.8
Classifier: Programming Language :: Python :: 3.9
Classifier: Programming Language :: Python :: 3.10
Classifier: Programming Language :: Python :: 3.11
Classifier: Programming Language :: Python :: 3.12
Classifier: Programming Language :: Python :: 3 :: Only
Classifier: License :: OSI Approved :: MIT License
Classifier: Operating System :: OS Independent
Classifier: Development Status :: 4 - Beta
Classifier: Intended Audience :: Developers
Classifier: Intended Audience :: Education
Classifier: Topic :: File Formats :: JSON
Classifier: Topic :: Games/Entertainment
Classifier: Topic :: Home Automation
Classifier: Topic :: Scientific/Engineering
Classifier: Topic :: Scientific/Engineering :: Electronic Design Automation (EDA)
Classifier: Topic :: Scientific/Engineering :: Human Machine Interfaces
Classifier: Topic :: Scientific/Engineering :: Information Analysis
Classifier: Topic :: Scientific/Engineering :: Interface Engine/Protocol Translator
Classifier: Topic :: Software Development :: Assemblers
Classifier: Topic :: Software Development :: Build Tools
Classifier: Topic :: Software Development :: Code Generators
Classifier: Topic :: Software Development :: Compilers
Classifier: Topic :: Software Development :: Disassemblers
Classifier: Topic :: Software Development :: Embedded Systems
Classifier: Topic :: Software Development :: Libraries
Classifier: Topic :: Software Development :: Libraries :: Python Modules
Classifier: Topic :: System :: Hardware :: Hardware Drivers
Requires-Python: >=3.8
License-File: LICENSE.txt
Provides-Extra: examples
Requires-Dist: curses ; extra == 'examples'
